{
  "experiment": "compare_routers_10x10_392",
  "run_id": "cfa6a4450dda",
  "name": "classical_beam",
  "algorithm": "beam",
  "config": {
    "name": "classical_beam",
    "algorithm": "beam",
    "router_kwargs": {
      "max_layers": 1
    },
    "solve_kwargs": {},
    "metadata": {}
  },
  "router_state": {},
  "timestamp": "20251105_182056",
  "metrics": {
    "total_nets": 27,
    "routed_nets": 6,
    "total_length": 54,
    "total_turns": 9,
    "layers_used": 1,
    "cell_conflicts": 0
  }
}