{
  "experiment": "compare_routers_10x10_493",
  "run_id": "583101048611",
  "name": "classical_beam",
  "algorithm": "beam",
  "config": {
    "name": "classical_beam",
    "algorithm": "beam",
    "router_kwargs": {
      "max_layers": 1
    },
    "solve_kwargs": {},
    "metadata": {}
  },
  "router_state": {},
  "timestamp": "20251105_184834",
  "metrics": {
    "total_nets": 22,
    "routed_nets": 5,
    "total_length": 55,
    "total_turns": 10,
    "layers_used": 1,
    "cell_conflicts": 0
  }
}