{
  "experiment": "compare_routers_10x10_833",
  "run_id": "946a7710dd35",
  "config": {
    "name": "classical_wave",
    "algorithm": "wave",
    "router_kwargs": {
      "max_layers": 1
    },
    "solve_kwargs": {},
    "metadata": {}
  },
  "algorithm": "wave",
  "timestamp": "20251105_202854",
  "total_nets": 4,
  "routed_net_names": [
    "Net_1",
    "Net_2",
    "Net_3",
    "Net_4"
  ],
  "unrouted_net_names": [],
  "net_pin_mapping": {
    "Net_1": {
      "src_pin": "P2",
      "dst_pin": "P1"
    },
    "Net_2": {
      "src_pin": "P4",
      "dst_pin": "P2"
    },
    "Net_3": {
      "src_pin": "P3",
      "dst_pin": "P1"
    },
    "Net_4": {
      "src_pin": "P4",
      "dst_pin": "P1"
    }
  },
  "router_state": {},
  "paths": {
    "Net_1": [
      [
        9,
        3,
        0
      ],
      [
        8,
        3,
        0
      ],
      [
        7,
        3,
        0
      ],
      [
        7,
        2,
        0
      ],
      [
        6,
        2,
        0
      ],
      [
        5,
        2,
        0
      ],
      [
        4,
        2,
        0
      ]
    ],
    "Net_2": [
      [
        7,
        1,
        0
      ],
      [
        8,
        1,
        0
      ],
      [
        8,
        2,
        0
      ],
      [
        9,
        2,
        0
      ],
      [
        9,
        3,
        0
      ]
    ],
    "Net_3": [
      [
        5,
        9,
        0
      ],
      [
        5,
        8,
        0
      ],
      [
        5,
        7,
        0
      ],
      [
        5,
        6,
        0
      ],
      [
        5,
        5,
        0
      ],
      [
        5,
        4,
        0
      ],
      [
        5,
        3,
        0
      ],
      [
        4,
        3,
        0
      ],
      [
        4,
        2,
        0
      ]
    ],
    "Net_4": [
      [
        7,
        1,
        0
      ],
      [
        6,
        1,
        0
      ],
      [
        5,
        1,
        0
      ],
      [
        4,
        1,
        0
      ],
      [
        4,
        2,
        0
      ]
    ]
  },
  "cell_conflicts": 0,
  "conflict_cells": []
}