{
  "experiment": "compare_routers_10x10_860",
  "run_id": "4c998a6caa9d",
  "name": "classical_wave",
  "algorithm": "wave",
  "config": {
    "name": "classical_wave",
    "algorithm": "wave",
    "router_kwargs": {
      "max_layers": 1
    },
    "solve_kwargs": {},
    "metadata": {}
  },
  "router_state": {},
  "timestamp": "20251105_203700",
  "metrics": {
    "total_nets": 8,
    "routed_nets": 5,
    "total_length": 38,
    "total_turns": 9,
    "layers_used": 1,
    "cell_conflicts": 0
  }
}