{
  "experiment": "compare_routers_10x10_232",
  "run_id": "df20979a5c45",
  "name": "classical_wave",
  "algorithm": "wave",
  "config": {
    "name": "classical_wave",
    "algorithm": "wave",
    "router_kwargs": {
      "max_layers": 1
    },
    "solve_kwargs": {},
    "metadata": {}
  },
  "router_state": {},
  "timestamp": "20251105_173621",
  "metrics": {
    "total_nets": 20,
    "routed_nets": 6,
    "total_length": 40,
    "total_turns": 13,
    "layers_used": 1,
    "cell_conflicts": 0
  }
}