{
  "experiment": "compare_routers_10x10_761",
  "run_id": "2c1e984fa5b1",
  "name": "classical_wave",
  "algorithm": "wave",
  "config": {
    "name": "classical_wave",
    "algorithm": "wave",
    "router_kwargs": {
      "max_layers": 1
    },
    "solve_kwargs": {},
    "metadata": {}
  },
  "router_state": {},
  "timestamp": "20251105_200807",
  "metrics": {
    "total_nets": 16,
    "routed_nets": 9,
    "total_length": 53,
    "total_turns": 15,
    "layers_used": 1,
    "cell_conflicts": 0
  }
}