{
  "experiment": "compare_routers_10x10_23",
  "run_id": "daec98e8c171",
  "name": "classical_wave",
  "algorithm": "wave",
  "config": {
    "name": "classical_wave",
    "algorithm": "wave",
    "router_kwargs": {
      "max_layers": 1
    },
    "solve_kwargs": {},
    "metadata": {}
  },
  "router_state": {},
  "timestamp": "20251105_163442",
  "metrics": {
    "total_nets": 4,
    "routed_nets": 4,
    "total_length": 38,
    "total_turns": 6,
    "layers_used": 1,
    "cell_conflicts": 0
  }
}