{
  "experiment": "compare_routers_10x10_966",
  "rows": 10,
  "cols": 10,
  "blocked": [],
  "total_nets": 9,
  "pins": {
    "P1": {
      "coords": [
        2,
        6,
        0
      ]
    },
    "P2": {
      "coords": [
        3,
        0,
        0
      ]
    }
  },
  "nets": [
    {
      "name": "Net_1",
      "src_pin": "P1",
      "dst_pin": "P2",
      "src": [
        2,
        6,
        0
      ],
      "dst": [
        3,
        0,
        0
      ]
    },
    {
      "name": "Net_2",
      "src_pin": "P1",
      "dst_pin": "P2",
      "src": [
        2,
        6,
        0
      ],
      "dst": [
        3,
        0,
        0
      ]
    },
    {
      "name": "Net_3",
      "src_pin": "P2",
      "dst_pin": "P1",
      "src": [
        3,
        0,
        0
      ],
      "dst": [
        2,
        6,
        0
      ]
    },
    {
      "name": "Net_4",
      "src_pin": "P1",
      "dst_pin": "P2",
      "src": [
        2,
        6,
        0
      ],
      "dst": [
        3,
        0,
        0
      ]
    },
    {
      "name": "Net_5",
      "src_pin": "P1",
      "dst_pin": "P2",
      "src": [
        2,
        6,
        0
      ],
      "dst": [
        3,
        0,
        0
      ]
    },
    {
      "name": "Net_6",
      "src_pin": "P2",
      "dst_pin": "P1",
      "src": [
        3,
        0,
        0
      ],
      "dst": [
        2,
        6,
        0
      ]
    },
    {
      "name": "Net_7",
      "src_pin": "P2",
      "dst_pin": "P1",
      "src": [
        3,
        0,
        0
      ],
      "dst": [
        2,
        6,
        0
      ]
    },
    {
      "name": "Net_8",
      "src_pin": "P2",
      "dst_pin": "P1",
      "src": [
        3,
        0,
        0
      ],
      "dst": [
        2,
        6,
        0
      ]
    },
    {
      "name": "Net_9",
      "src_pin": "P2",
      "dst_pin": "P1",
      "src": [
        3,
        0,
        0
      ],
      "dst": [
        2,
        6,
        0
      ]
    }
  ],
  "created_at": "20251105_211208"
}