{
  "experiment": "compare_routers_10x10_547",
  "run_id": "c85bf41f5993",
  "name": "classical_beam",
  "algorithm": "beam",
  "config": {
    "name": "classical_beam",
    "algorithm": "beam",
    "router_kwargs": {
      "max_layers": 1
    },
    "solve_kwargs": {},
    "metadata": {}
  },
  "router_state": {},
  "timestamp": "20251105_190454",
  "metrics": {
    "total_nets": 3,
    "routed_nets": 3,
    "total_length": 26,
    "total_turns": 4,
    "layers_used": 1,
    "cell_conflicts": 0
  }
}