{
  "experiment": "compare_routers_10x10_951",
  "rows": 10,
  "cols": 10,
  "blocked": [],
  "total_nets": 4,
  "pins": {
    "P5": {
      "coords": [
        7,
        0,
        0
      ]
    },
    "P2": {
      "coords": [
        1,
        8,
        0
      ]
    },
    "P4": {
      "coords": [
        9,
        8,
        0
      ]
    },
    "P1": {
      "coords": [
        7,
        8,
        0
      ]
    }
  },
  "nets": [
    {
      "name": "Net_1",
      "src_pin": "P5",
      "dst_pin": "P2",
      "src": [
        7,
        0,
        0
      ],
      "dst": [
        1,
        8,
        0
      ]
    },
    {
      "name": "Net_2",
      "src_pin": "P5",
      "dst_pin": "P2",
      "src": [
        7,
        0,
        0
      ],
      "dst": [
        1,
        8,
        0
      ]
    },
    {
      "name": "Net_3",
      "src_pin": "P2",
      "dst_pin": "P4",
      "src": [
        1,
        8,
        0
      ],
      "dst": [
        9,
        8,
        0
      ]
    },
    {
      "name": "Net_4",
      "src_pin": "P5",
      "dst_pin": "P1",
      "src": [
        7,
        0,
        0
      ],
      "dst": [
        7,
        8,
        0
      ]
    }
  ],
  "created_at": "20251105_210711"
}